crewai/__init__.py
crewai/agent.py
crewai/agents/__init__.py
crewai/agents/agent_builder/__init__.py
crewai/agents/agent_builder/base_agent.py
crewai/agents/agent_builder/base_agent_executor_mixin.py
crewai/agents/agent_builder/utilities/__init__.py
crewai/agents/agent_builder/utilities/base_agent_tool.py
crewai/agents/agent_builder/utilities/base_output_converter.py
crewai/agents/agent_builder/utilities/base_token_process.py
crewai/agents/cache/__init__.py
crewai/agents/cache/cache_handler.py
crewai/agents/executor.py
crewai/agents/parser.py
crewai/agents/tools_handler.py
crewai/cli/__init__.py
crewai/cli/cli.py
crewai/cli/create_crew.py
crewai/cli/replay_from_task.py
crewai/cli/reset_memories_command.py
crewai/cli/templates/.gitignore
crewai/cli/templates/README.md
crewai/cli/templates/__init__.py
crewai/cli/templates/config/agents.yaml
crewai/cli/templates/config/tasks.yaml
crewai/cli/templates/crew.py
crewai/cli/templates/main.py
crewai/cli/templates/pyproject.toml
crewai/cli/templates/tools/__init__.py
crewai/cli/templates/tools/custom_tool.py
crewai/cli/train_crew.py
crewai/crew.py
crewai/crews/__init__.py
crewai/crews/crew_output.py
crewai/memory/__init__.py
crewai/memory/contextual/__init__.py
crewai/memory/contextual/contextual_memory.py
crewai/memory/entity/__init__.py
crewai/memory/entity/entity_memory.py
crewai/memory/entity/entity_memory_item.py
crewai/memory/long_term/__init__.py
crewai/memory/long_term/long_term_memory.py
crewai/memory/long_term/long_term_memory_item.py
crewai/memory/memory.py
crewai/memory/short_term/__init__.py
crewai/memory/short_term/short_term_memory.py
crewai/memory/short_term/short_term_memory_item.py
crewai/memory/storage/interface.py
crewai/memory/storage/kickoff_task_outputs_storage.py
crewai/memory/storage/ltm_sqlite_storage.py
crewai/memory/storage/rag_storage.py
crewai/process.py
crewai/project/__init__.py
crewai/project/annotations.py
crewai/project/crew_base.py
crewai/task.py
crewai/tasks/__init__.py
aipmai-0.41.0.dist-info/LICENSE
aipmai-0.41.0.dist-info/METADATA
aipmai-0.41.0.dist-info/WHEEL
aipmai-0.41.0.dist-info/entry_points.txt
aipmai-0.41.0.dist-info/RECORD
