Metadata-Version: 2.1
Name: aipmai
Version: 0.41.0
Summary: Cutting-edge framework for orchestrating role-playing, autonomous AI agents. By fostering collaborative intelligence, CrewAI empowers agents to work together seamlessly, tackling complex tasks. (Chinese Version)
Author: AiPMHub
Author-email: nextprofessionalpower@gmail.com
Requires-Python: >=3.10,<=3.13
Classifier: Programming Language :: Python :: 3
Classifier: Programming Language :: Python :: 3.10
Classifier: Programming Language :: Python :: 3.11
Classifier: Programming Language :: Python :: 3.12
Provides-Extra: agentops
Provides-Extra: tools
Requires-Dist: agentops (>=0.3.0,<0.4.0) ; extra == "agentops"
Requires-Dist: aipmai-tools (>=0.4.26,<0.5.0) ; extra == "tools"
Requires-Dist: appdirs (>=1.4.4,<2.0.0)
Requires-Dist: click (>=8.1.7,<9.0.0)
Requires-Dist: embedchain (>=0.1.114,<0.2.0)
Requires-Dist: instructor (==1.3.3)
Requires-Dist: json-repair (>=0.25.2,<0.26.0)
Requires-Dist: jsonref (>=1.1.0,<2.0.0)
Requires-Dist: langchain (>0.2,<=0.3)
Requires-Dist: openai (>=1.13.3,<2.0.0)
Requires-Dist: opentelemetry-api (>=1.22.0,<2.0.0)
Requires-Dist: opentelemetry-exporter-otlp-proto-http (>=1.22.0,<2.0.0)
Requires-Dist: opentelemetry-sdk (>=1.22.0,<2.0.0)
Requires-Dist: pydantic (>=2.4.2,<3.0.0)
Requires-Dist: python-dotenv (>=1.0.0,<2.0.0)
Requires-Dist: regex (>=2023.12.25,<2024.0.0)
Project-URL: Documentation, https://github.com/aithoughts/aipmAI/wiki/Index
Project-URL: Homepage, https://www.theforage.cn
Project-URL: Repository, https://github.com/aithoughts/aipmAI
